config/__init__.py
config/global_variable.py
crawler/__init__.py
crawler/base_crawler.py
crawler/codeforces_crawler.py
models/__init__.py
models/base_model.py
models/codeforces_model.py
tools/__init__.py
tools/diy_logger.py
tools/register_config.py
oiCrawer-0.1.1.dist-info/METADATA
oiCrawer-0.1.1.dist-info/WHEEL
oiCrawer-0.1.1.dist-info/top_level.txt
oiCrawer-0.1.1.dist-info/RECORD
