Metadata-Version: 2.1
Name: oiCrawer
Version: 0.1.1
Summary: tool for crawing info about website on oier or acmer
Home-page: https://github.com/CoolGuang/oiCrawer
Author: CCoolGuang
Author-email: xwgsocool@gmail.com
License: Apache
Classifier: License :: OSI Approved :: MIT License
Classifier: Programming Language :: Python
Classifier: Programming Language :: Python :: 3
Classifier: Programming Language :: Python :: 3.6
Classifier: Programming Language :: Python :: Implementation :: CPython
Classifier: Programming Language :: Python :: Implementation :: PyPy
Requires-Python: >=3.6.0
Requires-Dist: requests (==2.28.1)
Requires-Dist: bs4 (==0.0.1)
Requires-Dist: lxml (==4.9.1)
